Metadata-Version: 1.1
Name: sgdhfdhfjjfk
Version: 1.2.0
Summary: A sample Python project
Home-page: https://github.com/pypa/sampleproject
Author: The Python Packaging Authority
Author-email: pypa-dev@googlegroups.com
License: MIT
Keywords: sample setuptools development
Platform: UNKNOWN
Classifier: Development Status :: 3 - Alpha
Classifier: Intended Audience :: Developers
Classifier: Topic :: Software Development :: Build Tools
Classifier: License :: OSI Approved :: MIT License
Classifier: Programming Language :: Python :: 2
Classifier: Programming Language :: Python :: 2.7
Classifier: Programming Language :: Python :: 3
Classifier: Programming Language :: Python :: 3.3
Classifier: Programming Language :: Python :: 3.4
Classifier: Programming Language :: Python :: 3.5
